library/__init__.py
anython-1.1.dist-info/LICENSE.txt
anython-1.1.dist-info/METADATA
anython-1.1.dist-info/WHEEL
anython-1.1.dist-info/top_level.txt
anython-1.1.dist-info/RECORD
