Metadata-Version: 2.1
Name: anython
Version: 1.1
Summary: no dec
Author: defzaid
Classifier: Programming Language :: Python :: 3
Classifier: License :: OSI Approved :: MIT License
Classifier: Operating System :: OS Independent
Requires-Python: >=3.12
License-File: LICENSE.txt
Requires-Dist: anython >=1.0
Requires-Dist: kivy >=2.3.0
